{
  "Ads": [
    {
      "status_app": "0",
      "link_redirect": "",
      "select_exit": "2",
      "on_off_category": "3",
      "on_off_more_app": "3"
    }
  ],
  "Data": [
    {
      "id": 1001,
      "name_category": "Nature",
      "title": "Wallpaper_offline_01",
      "image": "file:///android_asset/image/wallpaper_01.jpg"
    },
    {
      "id": 1002,
      "name_category": "Nature",
      "title": "Wallpaper_offline_02",
      "image": "file:///android_asset/image/wallpaper_02.jpg"
    },
    {
      "id": 1003,
      "name_category": "Nature",
      "title": "Wallpaper_offline_03",
      "image": "file:///android_asset/image/wallpaper_03.jpg"
    },
    {
      "id": 1004,
      "name_category": "Nature",
      "title": "Wallpaper_offline_04",
      "image": "file:///android_asset/image/wallpaper_04.jpg"
    },
    {
      "id": 1005,
      "name_category": "Nature",
      "title": "Wallpaper_offline_05",
      "image": "file:///android_asset/image/wallpaper_05.jpg"
    },
    {
      "id": 1006,
      "name_category": "Nature",
      "title": "Wallpaper_offline_06",
      "image": "file:///android_asset/image/wallpaper_06.jpg"
    },
    {
      "id": 1007,
      "name_category": "Nature",
      "title": "Wallpaper_offline_07",
      "image": "file:///android_asset/image/wallpaper_07.jpg"
    },
    {
      "id": 1008,
      "name_category": "Nature",
      "title": "Wallpaper_offline_08",
      "image": "file:///android_asset/image/wallpaper_08.jpg"
    },
    {
      "id": 1009,
      "name_category": "Nature",
      "title": "Wallpaper_offline_09",
      "image": "file:///android_asset/image/wallpaper_09.jpg"
    },
    {
      "id": 1010,
      "name_category": "Nature",
      "title": "Wallpaper_offline_10",
      "image": "file:///android_asset/image/wallpaper_10.jpg"
    },
    {
      "id": 1,
      "name_category": "Nature",
      "title": "Wallpaper_01",
      "image": "https://i.pinimg.com/originals/36/f0/85/36f0850e0b2487caaa3a72016b463751.jpg"
    },
    {
      "id": 2,
      "name_category": "Nature",
      "title": "Wallpaper_02",
      "image": "https://i.pinimg.com/originals/5b/35/41/5b3541af12c132ac9eedf663b8b03081.jpg"
    },
    {
      "id": 3,
      "name_category": "Nature",
      "title": "Wallpaper_03",
      "image": "https://i.pinimg.com/originals/87/f5/d1/87f5d16c75abf315252cd8275828402e.png"
    },
    {
      "id": 4,
      "name_category": "Nature",
      "title": "Wallpaper_04",
      "image": "https://i.pinimg.com/originals/50/d6/1e/50d61ebac0036a68a924efd3492261e6.jpg"
    },
    {
      "id": 5,
      "name_category": "Nature",
      "title": "Wallpaper_05",
      "image": "https://i.pinimg.com/originals/b7/58/56/b75856bded393fa0b34ef43f23937375.jpg"
    },
    {
      "id": 6,
      "name_category": "Nature",
      "title": "Wallpaper_06",
      "image": "https://i.pinimg.com/originals/08/19/c2/0819c2c04614cee2f6a6afcc0c6c78a2.jpg"
    },
    {
      "id": 7,
      "name_category": "Nature",
      "title": "Wallpaper_07",
      "image": "https://i.pinimg.com/originals/91/32/79/913279ad7f860ff6a53b8456a037a245.jpg"
    },
    {
      "id": 8,
      "name_category": "Nature",
      "title": "Wallpaper_08",
      "image": "https://i.pinimg.com/originals/b5/26/a2/b526a2e16a0579508956189c7b4a2918.jpg"
    },
    {
      "id": 9,
      "name_category": "Nature",
      "title": "Wallpaper_09",
      "image": "https://i.pinimg.com/originals/1e/61/16/1e611676f61cea53f295d119b96b0553.jpg"
    },
    {
      "id": 10,
      "name_category": "Nature",
      "title": "Wallpaper_10",
      "image": "https://i.pinimg.com/originals/bd/01/30/bd0130f1535fc2ed37aa4a3f1a5fa34b.jpg"
    },
    {
      "id": 11,
      "name_category": "Nature",
      "title": "Wallpaper_11",
      "image": "https://i.pinimg.com/originals/84/ce/f0/84cef026ba8336f800a586866c0cd512.jpg"
    },
    {
      "id": 12,
      "name_category": "Nature",
      "title": "Wallpaper_12",
      "image": "https://i.pinimg.com/originals/ff/10/2c/ff102c68986c6fc4a05894394a818f43.jpg"
    },
    {
      "id": 13,
      "name_category": "Nature",
      "title": "Wallpaper_13",
      "image": "https://i.pinimg.com/originals/13/d7/76/13d7762cfbb57bfc65d1049a7ee723de.jpg"
    },
    {
      "id": 14,
      "name_category": "Nature",
      "title": "Wallpaper_14",
      "image": "https://i.pinimg.com/originals/c1/0b/25/c10b2599d6ef91204b79d4067b6a3214.jpg"
    },
    {
      "id": 15,
      "name_category": "Nature",
      "title": "Wallpaper_15",
      "image": "https://i.pinimg.com/originals/35/33/fc/3533fc41477c12768a4781937cc508f6.jpg"
    },
    {
      "id": 16,
      "name_category": "Nature",
      "title": "Wallpaper_16",
      "image": "https://i.pinimg.com/originals/59/dc/ba/59dcba684eb10828325caea5a61da15b.jpg"
    },
    {
      "id": 17,
      "name_category": "Nature",
      "title": "Wallpaper_17",
      "image": "https://i.pinimg.com/originals/78/53/8f/78538f7c38b14d363a86092ef08daa35.jpg"
    },
    {
      "id": 18,
      "name_category": "Nature",
      "title": "Wallpaper_18",
      "image": "https://i.pinimg.com/originals/e2/06/3e/e2063e84da6e9b2a515a587448b5bd49.jpg"
    },
    {
      "id": 19,
      "name_category": "Nature",
      "title": "Wallpaper_19",
      "image": "https://i.pinimg.com/originals/d7/84/6a/d7846a7d50eacc7609c8e18d0e15c3d4.jpg"
    },
    {
      "id": 20,
      "name_category": "Nature",
      "title": "Wallpaper_20",
      "image": "https://i.pinimg.com/originals/20/20/61/202061d665317a3b990f6a7105251979.jpg"
    },
    {
      "id": 21,
      "name_category": "Nature",
      "title": "Wallpaper_21",
      "image": "https://i.pinimg.com/originals/8a/be/a7/8abea7e0df18e130741ade4adefdfa90.jpg"
    },
    {
      "id": 22,
      "name_category": "Nature",
      "title": "Wallpaper_22",
      "image": "https://i.pinimg.com/originals/2f/fc/c1/2ffcc1a7683879d6724e2b5c9026760b.jpg"
    },
    {
      "id": 23,
      "name_category": "Nature",
      "title": "Wallpaper_23",
      "image": "https://i.pinimg.com/originals/db/4b/c4/db4bc4f079396b4577b83ac808da1139.jpg"
    },
    {
      "id": 24,
      "name_category": "Nature",
      "title": "Wallpaper_24",
      "image": "https://i.pinimg.com/originals/11/30/cd/1130cd70d2cf986ea0d23341c9249ce5.jpg"
    },
    {
      "id": 25,
      "name_category": "Nature",
      "title": "Wallpaper_25",
      "image": "https://i.pinimg.com/originals/53/25/c3/5325c3e10e730ff91f0b783949f10d82.jpg"
    },
    {
      "id": 26,
      "name_category": "Nature",
      "title": "Wallpaper_26",
      "image": "https://i.pinimg.com/originals/63/56/c2/6356c2f270976bfc1cb6d5a7951e5875.jpg"
    },
    {
      "id": 27,
      "name_category": "Nature",
      "title": "Wallpaper_27",
      "image": "https://i.pinimg.com/originals/66/26/55/66265551009e6b1168b843333470a4e7.png"
    },
    {
      "id": 28,
      "name_category": "Nature",
      "title": "Wallpaper_28",
      "image": "https://i.pinimg.com/originals/ee/4f/bf/ee4fbfd31840a2891fda50712f64a2a5.jpg"
    },
    {
      "id": 29,
      "name_category": "Nature",
      "title": "Wallpaper_29",
      "image": "https://i.pinimg.com/originals/99/8d/6f/998d6f69148ea8de8b75863cea850761.jpg"
    },
    {
      "id": 30,
      "name_category": "Nature",
      "title": "Wallpaper_30",
      "image": "https://i.pinimg.com/originals/86/44/16/8644167be895b1078e1678a02d4d6393.jpg"
    },
    {
      "id": 31,
      "name_category": "Nature",
      "title": "Wallpaper_31",
      "image": "https://i.pinimg.com/originals/a3/87/72/a387723c01280c2f5bebceafa05d3812.jpg"
    },
    {
      "id": 32,
      "name_category": "Nature",
      "title": "Wallpaper_32",
      "image": "https://i.pinimg.com/originals/48/a6/5a/48a65a3b70e5ed6cf1e9d41ea0eb09da.jpg"
    },
    {
      "id": 33,
      "name_category": "Nature",
      "title": "Wallpaper_33",
      "image": "https://i.pinimg.com/originals/46/6f/d4/466fd4f805b7a991a1a4d285df42d1b7.png"
    },
    {
      "id": 34,
      "name_category": "Nature",
      "title": "Wallpaper_34",
      "image": "https://i.pinimg.com/originals/d1/8c/22/d18c2233c2083543405c19b2343f75a3.jpg"
    },
    {
      "id": 35,
      "name_category": "Nature",
      "title": "Wallpaper_35",
      "image": "https://i.pinimg.com/originals/68/5a/a1/685aa11370c25e710e3b666ffc5cc37b.jpg"
    },
    {
      "id": 36,
      "name_category": "Nature",
      "title": "Wallpaper_36",
      "image": "https://i.pinimg.com/originals/e1/fd/7e/e1fd7ed1c783fd6089a2f302e05b8751.jpg"
    },
    {
      "id": 37,
      "name_category": "Nature",
      "title": "Wallpaper_37",
      "image": "https://i.pinimg.com/originals/f7/4a/49/f74a49963c3570fb9436fd69322bbdf6.jpg"
    },
    {
      "id": 38,
      "name_category": "Nature",
      "title": "Wallpaper_38",
      "image": "https://i.pinimg.com/originals/24/a8/39/24a8397f7c04aeee7522affed2b816f3.jpg"
    },
    {
      "id": 39,
      "name_category": "Nature",
      "title": "Wallpaper_39",
      "image": "https://i.pinimg.com/originals/a0/52/d8/a052d8401e9214f7bd43832ace3e969d.jpg"
    },
    {
      "id": 40,
      "name_category": "Nature",
      "title": "Wallpaper_40",
      "image": "https://i.pinimg.com/originals/71/8d/58/718d581b6ce5f3b093007ce7b3a23e80.jpg"
    },
    {
      "id": 41,
      "name_category": "Nature",
      "title": "Wallpaper_41",
      "image": "https://i.pinimg.com/originals/bb/e6/e4/bbe6e48bbd2f25df3a9e6578b6f95856.jpg"
    },
    {
      "id": 42,
      "name_category": "Nature",
      "title": "Wallpaper_42",
      "image": "https://i.pinimg.com/originals/e4/75/85/e475854d02b4761447822f1d525d5149.png"
    },
    {
      "id": 43,
      "name_category": "Nature",
      "title": "Wallpaper_43",
      "image": "https://i.pinimg.com/originals/b8/8b/a5/b88ba523a6d0eb608791ec6cde748e5b.png"
    },
    {
      "id": 44,
      "name_category": "Nature",
      "title": "Wallpaper_44",
      "image": "https://i.pinimg.com/originals/77/69/6e/77696e47a32d9bf1d6bd760a0a3443ff.jpg"
    },
    {
      "id": 45,
      "name_category": "Nature",
      "title": "Wallpaper_45",
      "image": "https://i.pinimg.com/originals/b0/b6/2e/b0b62e98112e2ac6ea01b4e33c172a8e.jpg"
    },
    {
      "id": 46,
      "name_category": "Nature",
      "title": "Wallpaper_46",
      "image": "https://i.pinimg.com/originals/a1/dc/39/a1dc39ef5f8335ff8df0d1b9b84bb65b.jpg"
    },
    {
      "id": 47,
      "name_category": "Nature",
      "title": "Wallpaper_47",
      "image": "https://i.pinimg.com/originals/7a/a9/ba/7aa9ba171243c8dceb42b742e09981c2.jpg"
    },
    {
      "id": 48,
      "name_category": "Nature",
      "title": "Wallpaper_48",
      "image": "https://i.pinimg.com/originals/69/71/03/6971030edd37fe3aa9c1f1e6c969011c.jpg"
    },
    {
      "id": 49,
      "name_category": "Nature",
      "title": "Wallpaper_49",
      "image": "https://i.pinimg.com/originals/30/93/d7/3093d76f291e507266aa556c048d1631.jpg"
    },
    {
      "id": 50,
      "name_category": "Nature",
      "title": "Wallpaper_50",
      "image": "https://i.pinimg.com/originals/62/f1/88/62f188d91415207453de65520902b2b5.jpg"
    },
    {
      "id": 51,
      "name_category": "Nature",
      "title": "Wallpaper_51",
      "image": "https://i.pinimg.com/originals/0a/82/73/0a827303ca564a75fccb843629b983fc.jpg"
    },
    {
      "id": 52,
      "name_category": "Nature",
      "title": "Wallpaper_52",
      "image": "https://i.pinimg.com/originals/81/a5/9c/81a59c230531520eb0d5c7c127aa857b.png"
    },
    {
      "id": 53,
      "name_category": "Nature",
      "title": "Wallpaper_53",
      "image": "https://i.pinimg.com/originals/19/b6/b3/19b6b3949e3bc8fe815a60d6d0b9dfb3.jpg"
    },
    {
      "id": 54,
      "name_category": "Nature",
      "title": "Wallpaper_54",
      "image": "https://i.pinimg.com/originals/2e/3c/3d/2e3c3d1f0f515c5bc6e181878b02ea46.jpg"
    },
    {
      "id": 55,
      "name_category": "Nature",
      "title": "Wallpaper_55",
      "image": "https://i.pinimg.com/originals/60/b7/a9/60b7a9f6fe6a1ac1d7fbfd395629728a.jpg"
    },
    {
      "id": 56,
      "name_category": "Nature",
      "title": "Wallpaper_56",
      "image": "https://i.pinimg.com/originals/e2/df/a6/e2dfa6e624d2f2e59414d52d3cca933a.jpg"
    },
    {
      "id": 57,
      "name_category": "Nature",
      "title": "Wallpaper_57",
      "image": "https://i.pinimg.com/originals/25/93/a4/2593a476d6d2ed26c2e170aef6195559.jpg"
    },
    {
      "id": 58,
      "name_category": "Nature",
      "title": "Wallpaper_58",
      "image": "https://i.pinimg.com/originals/3e/a9/ba/3ea9ba9e84ab6808a394b6aa165c1673.jpg"
    },
    {
      "id": 59,
      "name_category": "Nature",
      "title": "Wallpaper_59",
      "image": "https://i.pinimg.com/originals/7a/6f/ce/7a6fce20632c3e6e1d51277c823625e1.jpg"
    },
    {
      "id": 60,
      "name_category": "Nature",
      "title": "Wallpaper_60",
      "image": "https://i.pinimg.com/originals/63/0d/39/630d3948df4a9d761cf9df183e514557.jpg"
    },
    {
      "id": 61,
      "name_category": "Nature",
      "title": "Wallpaper_61",
      "image": "https://i.pinimg.com/originals/58/be/78/58be78fd6f564eb5dd358b2bd82c6a03.jpg"
    },
    {
      "id": 62,
      "name_category": "Nature",
      "title": "Wallpaper_62",
      "image": "https://i.pinimg.com/originals/11/20/93/11209390a2b8d633c277e798ae8a7520.jpg"
    },
    {
      "id": 63,
      "name_category": "Nature",
      "title": "Wallpaper_63",
      "image": "https://i.pinimg.com/originals/ce/b3/b1/ceb3b1a3cc3dc8196b552954ced99120.jpg"
    },
    {
      "id": 64,
      "name_category": "Nature",
      "title": "Wallpaper_64",
      "image": "https://i.pinimg.com/originals/19/fb/9e/19fb9e8562c13051134fd0d20a66bdfe.jpg"
    },
    {
      "id": 65,
      "name_category": "Nature",
      "title": "Wallpaper_65",
      "image": "https://i.pinimg.com/originals/8b/05/72/8b0572e25344576c01a12a4f015890d7.jpg"
    },
    {
      "id": 66,
      "name_category": "Nature",
      "title": "Wallpaper_66",
      "image": "https://i.pinimg.com/originals/1f/9c/34/1f9c34e92cd2c697823a9b6c4ba8d4df.jpg"
    },
    {
      "id": 67,
      "name_category": "Nature",
      "title": "Wallpaper_67",
      "image": "https://i.pinimg.com/originals/53/8c/20/538c209f19bad1668564e9022d42e8d0.jpg"
    },
    {
      "id": 68,
      "name_category": "Nature",
      "title": "Wallpaper_68",
      "image": "https://i.pinimg.com/originals/a2/81/93/a281939b6575649a895367cf485d31de.jpg"
    },
    {
      "id": 69,
      "name_category": "Nature",
      "title": "Wallpaper_69",
      "image": "https://i.pinimg.com/originals/3c/90/4c/3c904c26ed7ab1b31fd470f654d7f39a.jpg"
    },
    {
      "id": 70,
      "name_category": "Nature",
      "title": "Wallpaper_70",
      "image": "https://i.pinimg.com/originals/04/1a/72/041a7225805dbcf15cee170fb976a4c0.jpg"
    },
    {
      "id": 71,
      "name_category": "Nature",
      "title": "Wallpaper_71",
      "image": "https://i.pinimg.com/originals/1c/fd/75/1cfd750794e9a79edf7a2b7657337e82.jpg"
    },
    {
      "id": 72,
      "name_category": "Nature",
      "title": "Wallpaper_72",
      "image": "https://i.pinimg.com/originals/ae/ec/ae/aeecaea0b5d475b4fff6d1e1750fa7a8.jpg"
    },
    {
      "id": 73,
      "name_category": "Nature",
      "title": "Wallpaper_73",
      "image": "https://i.pinimg.com/originals/93/f4/96/93f4964cbf43a7df4938f9f8aee3ab93.jpg"
    },
    {
      "id": 74,
      "name_category": "Nature",
      "title": "Wallpaper_74",
      "image": "https://i.pinimg.com/originals/c9/01/a6/c901a613d6b2af289174ef38fe2e8d9a.jpg"
    },
    {
      "id": 75,
      "name_category": "Nature",
      "title": "Wallpaper_75",
      "image": "https://i.pinimg.com/originals/3f/37/0e/3f370e0a08efa6649d8dccb303067737.jpg"
    },
    {
      "id": 76,
      "name_category": "Nature",
      "title": "Wallpaper_76",
      "image": "https://i.pinimg.com/originals/cd/7c/e1/cd7ce1ef75cdb0416b7d2e15fe44ccea.jpg"
    },
    {
      "id": 77,
      "name_category": "Nature",
      "title": "Wallpaper_77",
      "image": "https://i.pinimg.com/originals/07/1e/e9/071ee99eac0ba187f6a52213fde8c745.png"
    },
    {
      "id": 78,
      "name_category": "Nature",
      "title": "Wallpaper_78",
      "image": "https://i.pinimg.com/originals/da/1a/f2/da1af2bd99f21a59505e9ab9b14cbde5.jpg"
    },
    {
      "id": 79,
      "name_category": "Nature",
      "title": "Wallpaper_79",
      "image": "https://i.pinimg.com/originals/26/95/47/269547357a867062d2583f34bcc7e981.png"
    },
    {
      "id": 80,
      "name_category": "Nature",
      "title": "Wallpaper_80",
      "image": "https://i.pinimg.com/originals/0c/92/f3/0c92f3b99b99d5ad525006d060bcccc4.jpg"
    }
  ]
}
