{
  "Ads": [
    {
      "status_app": "0",
      "link_redirect": "",
      "select_exit": "2",
      "on_off_category": "3",
      "on_off_more_app": "3"
    }
  ],
  "Data": [
    {
      "id": 1001,
      "name_category": "Nature",
      "title": "Wallpaper_offline _01",
      "image": "file:///android_asset/image/wallpaper_01.jpg"
    },
    {
      "id": 1002,
      "name_category": "Nature",
      "title": "Wallpaper_offline _02",
      "image": "file:///android_asset/image/wallpaper_02.jpg"
    },
    {
      "id": 1003,
      "name_category": "Nature",
      "title": "Wallpaper_offline _03",
      "image": "file:///android_asset/image/wallpaper_03.jpg"
    },
    {
      "id": 1004,
      "name_category": "Nature",
      "title": "Wallpaper_offline _04",
      "image": "file:///android_asset/image/wallpaper_04.jpg"
    },
    {
      "id": 1005,
      "name_category": "Nature",
      "title": "Wallpaper_offline _05",
      "image": "file:///android_asset/image/wallpaper_05.jpg"
    },
    {
      "id": 1006,
      "name_category": "Nature",
      "title": "Wallpaper_offline _06",
      "image": "file:///android_asset/image/wallpaper_06.jpg"
    },
    {
      "id": 1007,
      "name_category": "Nature",
      "title": "Wallpaper_offline _07",
      "image": "file:///android_asset/image/wallpaper_07.jpg"
    },
    {
      "id": 1008,
      "name_category": "Nature",
      "title": "Wallpaper_offline _08",
      "image": "file:///android_asset/image/wallpaper_08.jpg"
    },
    {
      "id": 1009,
      "name_category": "Nature",
      "title": "Wallpaper_offline _09",
      "image": "file:///android_asset/image/wallpaper_09.jpg"
    },
    {
      "id": 1010,
      "name_category": "Nature",
      "title": "Wallpaper_offline _10",
      "image": "file:///android_asset/image/wallpaper_10.jpg"
    },
    {
      "id": 1,
      "name_category": "Nature",
      "title": "Wallpaper_01",
      "image": "https://i.pinimg.com/originals/62/4f/d7/624fd7e6a8a2f555fc00b5947f498392.jpg"
    },
    {
      "id": 2,
      "name_category": "Nature",
      "title": "Wallpaper_02",
      "image": "https://i.pinimg.com/originals/b1/12/a2/b112a254dfffa73af988a0b6f118befb.jpg"
    },
    {
      "id": 3,
      "name_category": "Nature",
      "title": "Wallpaper_03",
      "image": "https://i.pinimg.com/originals/bf/1e/50/bf1e509f771336583975aa2e77bd7a09.jpg"
    },
    {
      "id": 4,
      "name_category": "Nature",
      "title": "Wallpaper_04",
      "image": "https://i.pinimg.com/originals/05/a2/b7/05a2b72a73f3e26ee72985b8364a78b4.jpg"
    },
    {
      "id": 5,
      "name_category": "Nature",
      "title": "Wallpaper_05",
      "image": "https://i.pinimg.com/originals/02/05/cf/0205cfc823c9e98d61aa3f7551a009e0.jpg"
    },
    {
      "id": 6,
      "name_category": "Nature",
      "title": "Wallpaper_06",
      "image": "https://i.pinimg.com/originals/16/e7/71/16e771d2662dca9211e0a4637368bdd1.jpg"
    },
    {
      "id": 7,
      "name_category": "Nature",
      "title": "Wallpaper_07",
      "image": "https://i.pinimg.com/originals/d1/89/5c/d1895c2cf7f56d5fbc77fd2aa1663380.jpg"
    },
    {
      "id": 8,
      "name_category": "Nature",
      "title": "Wallpaper_08",
      "image": "https://i.pinimg.com/originals/e0/97/c3/e097c3f89547f669c3f28ef8629c6bcc.jpg"
    },
    {
      "id": 9,
      "name_category": "Nature",
      "title": "Wallpaper_09",
      "image": "https://i.pinimg.com/originals/9d/4c/0c/9d4c0cbf03682b12321b605097b02ed9.jpg"
    },
    {
      "id": 10,
      "name_category": "Nature",
      "title": "Wallpaper_10",
      "image": "https://i.pinimg.com/originals/ae/c5/a0/aec5a0ff099a394c44ad8f30f91ca940.jpg"
    },
    {
      "id": 11,
      "name_category": "Nature",
      "title": "Wallpaper_11",
      "image": "https://i.pinimg.com/originals/eb/55/b0/eb55b0b3de0dbd75062b7eeaea7b8f1e.jpg"
    },
    {
      "id": 12,
      "name_category": "Nature",
      "title": "Wallpaper_12",
      "image": "https://i.pinimg.com/originals/0f/0c/0a/0f0c0ac6f30dd8c355ae9038ab440675.jpg"
    },
    {
      "id": 13,
      "name_category": "Nature",
      "title": "Wallpaper_13",
      "image": "https://i.pinimg.com/originals/1b/b5/bf/1bb5bf4df856f6bc04d4522e3d7ee84f.jpg"
    },
    {
      "id": 14,
      "name_category": "Nature",
      "title": "Wallpaper_14",
      "image": "https://i.pinimg.com/originals/d7/25/b2/d725b2361e1f005b7bae6d952a10a5f2.jpg"
    },
    {
      "id": 15,
      "name_category": "Nature",
      "title": "Wallpaper_15",
      "image": "https://i.pinimg.com/originals/2e/7f/5f/2e7f5f19a7a457bd57b2c091350939aa.jpg"
    },
    {
      "id": 16,
      "name_category": "Nature",
      "title": "Wallpaper_16",
      "image": "https://i.pinimg.com/originals/64/70/5f/64705f86df45ff30a0a5c34e2d5c6e8a.jpg"
    },
    {
      "id": 17,
      "name_category": "Nature",
      "title": "Wallpaper_17",
      "image": "https://i.pinimg.com/originals/bb/fd/a6/bbfda6b9ab9fdf103f592c9d1a996d25.jpg"
    },
    {
      "id": 18,
      "name_category": "Nature",
      "title": "Wallpaper_18",
      "image": "https://i.pinimg.com/originals/c2/78/87/c27887533e7010d44268b5dd6d0c80e3.jpg"
    },
    {
      "id": 19,
      "name_category": "Nature",
      "title": "Wallpaper_19",
      "image": "https://i.pinimg.com/originals/e5/b2/f4/e5b2f43a2c02a0734f835ede8149ca77.jpg"
    },
    {
      "id": 20,
      "name_category": "Nature",
      "title": "Wallpaper_20",
      "image": "https://i.pinimg.com/originals/54/4d/3b/544d3b43bebdb0b24d6480c5c9881975.gif"
    },
    {
      "id": 21,
      "name_category": "Nature",
      "title": "Wallpaper_21",
      "image": "https://i.pinimg.com/originals/51/a9/c2/51a9c2203ec191562af7d2d36f345fa3.jpg"
    },
    {
      "id": 22,
      "name_category": "Nature",
      "title": "Wallpaper_22",
      "image": "https://i.pinimg.com/originals/bd/ef/44/bdef44ecb8930a0e40bddd9aab582edb.jpg"
    },
    {
      "id": 23,
      "name_category": "Nature",
      "title": "Wallpaper_23",
      "image": "https://i.pinimg.com/originals/32/19/5c/32195c14ee8c2f4d17830c785e598041.jpg"
    },
    {
      "id": 24,
      "name_category": "Nature",
      "title": "Wallpaper_24",
      "image": "https://i.pinimg.com/originals/32/7a/1c/327a1c664ad3630a48b90655bb2dc14c.jpg"
    },
    {
      "id": 25,
      "name_category": "Nature",
      "title": "Wallpaper_25",
      "image": "https://i.pinimg.com/originals/82/85/07/828507a1c7c0b3e5480e75c0bcc9e300.jpg"
    },
    {
      "id": 26,
      "name_category": "Nature",
      "title": "Wallpaper_26",
      "image": "https://i.pinimg.com/originals/d9/53/fc/d953fc24e4c5087359cd8f214657b91b.jpg"
    },
    {
      "id": 27,
      "name_category": "Nature",
      "title": "Wallpaper_27",
      "image": "https://i.pinimg.com/originals/fc/bd/27/fcbd270ba95013ba647a94d943098d66.jpg"
    },
    {
      "id": 28,
      "name_category": "Nature",
      "title": "Wallpaper_28",
      "image": "https://i.pinimg.com/originals/9c/0a/8f/9c0a8fff236293338248b9a3305ed18a.jpg"
    },
    {
      "id": 29,
      "name_category": "Nature",
      "title": "Wallpaper_29",
      "image": "https://i.pinimg.com/originals/f0/3c/50/f03c50c7dee3ce4b231871050f13baad.jpg"
    },
    {
      "id": 30,
      "name_category": "Nature",
      "title": "Wallpaper_30",
      "image": "https://i.pinimg.com/originals/66/f9/8a/66f98a3ff5ecbdb82bd4c5453237d37a.jpg"
    },
    {
      "id": 31,
      "name_category": "Nature",
      "title": "Wallpaper_31",
      "image": "https://i.pinimg.com/originals/57/38/13/573813f43b3bb9fa3b0be75fdf28087f.jpg"
    },
    {
      "id": 32,
      "name_category": "Nature",
      "title": "Wallpaper_32",
      "image": "https://i.pinimg.com/originals/60/b3/1e/60b31e562bfc428b5d0d3a9d054b4d95.jpg"
    },
    {
      "id": 33,
      "name_category": "Nature",
      "title": "Wallpaper_33",
      "image": "https://i.pinimg.com/originals/d0/7b/89/d07b89aa212c25590b3706b5f2fca9a7.jpg"
    },
    {
      "id": 34,
      "name_category": "Nature",
      "title": "Wallpaper_34",
      "image": "https://i.pinimg.com/originals/d7/4d/76/d74d7687476091412307eb6945cd12fc.jpg"
    },
    {
      "id": 35,
      "name_category": "Nature",
      "title": "Wallpaper_35",
      "image": "https://i.pinimg.com/originals/cd/07/a4/cd07a47155d6370c03dacba9e4bb6518.jpg"
    },
    {
      "id": 36,
      "name_category": "Nature",
      "title": "Wallpaper_36",
      "image": "https://i.pinimg.com/originals/5d/c4/ec/5dc4ec6dc35f178510bde3f020e5a343.jpg"
    },
    {
      "id": 37,
      "name_category": "Nature",
      "title": "Wallpaper_37",
      "image": "https://i.pinimg.com/originals/ad/74/5a/ad745a668c705aa2dd02c6146b51e9f5.jpg"
    },
    {
      "id": 38,
      "name_category": "Nature",
      "title": "Wallpaper_38",
      "image": "https://i.pinimg.com/originals/9d/bc/a7/9dbca762e1774162eca79bea9b5774c2.jpg"
    },
    {
      "id": 39,
      "name_category": "Nature",
      "title": "Wallpaper_39",
      "image": "https://i.pinimg.com/originals/95/70/4d/95704d1ccdff22a4ef20b8c81bdc314d.jpg"
    },
    {
      "id": 40,
      "name_category": "Nature",
      "title": "Wallpaper_40",
      "image": "https://i.pinimg.com/originals/fc/24/44/fc244458fc732d5e16c5106a6c4f245c.jpg"
    },
    {
      "id": 41,
      "name_category": "Nature",
      "title": "Wallpaper_41",
      "image": "https://i.pinimg.com/originals/33/4b/8e/334b8e9f49d14e0b2f0a0daefaadf195.jpg"
    },
    {
      "id": 42,
      "name_category": "Nature",
      "title": "Wallpaper_42",
      "image": "https://i.pinimg.com/originals/db/3a/0e/db3a0ef3a85f3b39cd0c48dd99919c72.jpg"
    },
    {
      "id": 43,
      "name_category": "Nature",
      "title": "Wallpaper_43",
      "image": "https://i.pinimg.com/originals/af/84/80/af8480cad7177495694f2cab26281aeb.jpg"
    },
    {
      "id": 44,
      "name_category": "Nature",
      "title": "Wallpaper_44",
      "image": "https://i.pinimg.com/originals/50/4a/f4/504af4ecc28d6ae882011c0048792c34.png"
    },
    {
      "id": 45,
      "name_category": "Nature",
      "title": "Wallpaper_45",
      "image": "https://i.pinimg.com/originals/4c/35/37/4c353779d2c3c9d6851838019b54e47b.jpg"
    },
    {
      "id": 46,
      "name_category": "Nature",
      "title": "Wallpaper_46",
      "image": "https://i.pinimg.com/originals/24/1a/83/241a837d1b2a0c6db046e03c657d71f5.jpg"
    },
    {
      "id": 47,
      "name_category": "Nature",
      "title": "Wallpaper_47",
      "image": "https://i.pinimg.com/originals/9b/22/db/9b22dbc63cbbf62b98f6eec91e7b325c.jpg"
    },
    {
      "id": 48,
      "name_category": "Nature",
      "title": "Wallpaper_48",
      "image": "https://i.pinimg.com/originals/a4/ad/1a/a4ad1aa2dc5fcb9969516c6ea47224dd.jpg"
    },
    {
      "id": 49,
      "name_category": "Nature",
      "title": "Wallpaper_49",
      "image": "https://i.pinimg.com/originals/43/bc/03/43bc0388aa937b4c02752b72efa67b23.jpg"
    },
    {
      "id": 50,
      "name_category": "Nature",
      "title": "Wallpaper_50",
      "image": "https://i.pinimg.com/originals/e2/f8/b3/e2f8b3e71784df29549ce912d5933d2f.jpg"
    },
    {
      "id": 51,
      "name_category": "Nature",
      "title": "Wallpaper_51",
      "image": "https://i.pinimg.com/originals/a3/5a/a4/a35aa46c58396ecbada07013a19dcb6d.jpg"
    },
    {
      "id": 52,
      "name_category": "Nature",
      "title": "Wallpaper_52",
      "image": "https://i.pinimg.com/originals/9b/3e/fe/9b3efe3e4347f2fd93d21996fae87f14.jpg"
    },
    {
      "id": 53,
      "name_category": "Nature",
      "title": "Wallpaper_53",
      "image": "https://i.pinimg.com/originals/1f/d2/2e/1fd22e6e64555a797c2ce497cf9d16d7.jpg"
    },
    {
      "id": 54,
      "name_category": "Nature",
      "title": "Wallpaper_54",
      "image": "https://i.pinimg.com/originals/9b/0f/7a/9b0f7af6f570ef2ccf25de2c9ecb838a.jpg"
    },
    {
      "id": 55,
      "name_category": "Nature",
      "title": "Wallpaper_55",
      "image": "https://i.pinimg.com/originals/c0/82/65/c08265ce3815bae1d73553c726255a7f.jpg"
    },
    {
      "id": 56,
      "name_category": "Nature",
      "title": "Wallpaper_56",
      "image": "https://i.pinimg.com/originals/51/e2/6b/51e26b459711da36f36af335fbf9f18d.jpg"
    },
    {
      "id": 57,
      "name_category": "Nature",
      "title": "Wallpaper_57",
      "image": "https://i.pinimg.com/originals/5f/4d/ec/5f4dec1c422a2cd5eac4ac10dd8a96da.jpg"
    },
    {
      "id": 58,
      "name_category": "Nature",
      "title": "Wallpaper_58",
      "image": "https://i.pinimg.com/originals/b4/26/08/b426080c689927ab1e74d01536d4818e.jpg"
    },
    {
      "id": 59,
      "name_category": "Nature",
      "title": "Wallpaper_59",
      "image": "https://i.pinimg.com/originals/97/38/d3/9738d38f1f9eb1241a43900b704e02ac.jpg"
    },
    {
      "id": 60,
      "name_category": "Nature",
      "title": "Wallpaper_60",
      "image": "https://i.pinimg.com/originals/bd/31/04/bd31042d1d2844f780696c9af27bb61f.jpg"
    },
    {
      "id": 61,
      "name_category": "Nature",
      "title": "Wallpaper_61",
      "image": "https://i.pinimg.com/originals/13/07/7d/13077d62198ae7ffafb1858aa06be5b1.jpg"
    },
    {
      "id": 62,
      "name_category": "Nature",
      "title": "Wallpaper_62",
      "image": "https://i.pinimg.com/originals/6d/ea/9d/6dea9d05e1a53c128ac9b026e924b12c.png"
    },
    {
      "id": 63,
      "name_category": "Nature",
      "title": "Wallpaper_63",
      "image": "https://i.pinimg.com/originals/ff/91/36/ff9136af930d45e776b274423905a3d2.jpg"
    },
    {
      "id": 64,
      "name_category": "Nature",
      "title": "Wallpaper_64",
      "image": "https://i.pinimg.com/originals/2e/a4/5e/2ea45ecbd53e7e58dfa5a24cb6737016.jpg"
    },
    {
      "id": 65,
      "name_category": "Nature",
      "title": "Wallpaper_65",
      "image": "https://i.pinimg.com/originals/d2/bc/a9/d2bca9ce5dccc55c94187e8b7e71bfaf.jpg"
    },
    {
      "id": 66,
      "name_category": "Nature",
      "title": "Wallpaper_66",
      "image": "https://i.pinimg.com/originals/aa/f9/a4/aaf9a468db7f7154f769863fa58e08ce.jpg"
    },
    {
      "id": 67,
      "name_category": "Nature",
      "title": "Wallpaper_67",
      "image": "https://i.pinimg.com/originals/d8/3c/3b/d83c3bbc7706ec1c5d7265e01f7f6704.jpg"
    }
  ]
}